{"_path":"/networkengineer/dns","_dir":"networkengineer","_draft":false,"_partial":false,"_locale":"","title":"应用层","description":"","body":{"type":"root","children":[{"type":"element","tag":"h1","props":{"id":"应用层"},"children":[{"type":"text","value":"应用层"}]},{"type":"element","tag":"h2","props":{"id":"应用层概述"},"children":[{"type":"text","value":"应用层概述"}]},{"type":"element","tag":"ul","props":{},"children":[{"type":"element","tag":"li","props":{},"children":[{"type":"text","value":"直接为网络应用程序提供服务"}]}]},{"type":"element","tag":"h2","props":{"id":"常用的网络协议"},"children":[{"type":"text","value":"常用的网络协议"}]},{"type":"element","tag":"ul","props":{},"children":[{"type":"element","tag":"li","props":{},"children":[{"type":"text","value":"DNS,Http和Https,SMTP和POP3,FTP和Telnet,TCP和UDP,ICMP;"}]},{"type":"element","tag":"li","props":{},"children":[{"type":"text","value":"SSl技术"}]}]},{"type":"element","tag":"h2","props":{"id":"dns-domains-names-servers-域名解析系统"},"children":[{"type":"text","value":"DNS Domains Names Servers 域名解析系统"}]},{"type":"element","tag":"ul","props":{},"children":[{"type":"element","tag":"li","props":{},"children":[{"type":"text","value":"根域,顶级域名,二级域名,三级域名,四级域名"}]},{"type":"element","tag":"li","props":{},"children":[{"type":"text","value":"根域：."}]},{"type":"element","tag":"li","props":{},"children":[{"type":"text","value":"顶级域名：国家,类型,com,org,cn,mil(军事),gov(教育)"}]},{"type":"element","tag":"li","props":{},"children":[{"type":"text","value":"二级域名：可以自定义, 添加记录选择A记录,地址解析成域名"}]},{"type":"element","tag":"li","props":{},"children":[{"type":"text","value":"建立IP地址和域名之间的映射关系"}]},{"type":"element","tag":"li","props":{},"children":[{"type":"text","value":"如果没有DNS服务器，所有的域名无法访问；"}]}]},{"type":"element","tag":"h2","props":{"id":"dns解析过程"},"children":[{"type":"text","value":"DNS解析过程"}]},{"type":"element","tag":"ul","props":{},"children":[{"type":"element","tag":"li","props":{},"children":[{"type":"text","value":"发送DNS请求到DNS服务器,查看是否有记录,有记录,发送数据宝,没有记录,发送DNS请求到根域,根域返回顶级域,顶级域返回二级域,二级域返回IP地址,返回IP地址"}]},{"type":"element","tag":"li","props":{},"children":[{"type":"text","value":"别名：CNAME"}]},{"type":"element","tag":"li","props":{},"children":[{"type":"text","value":"nslookup DNS调试工具"}]},{"type":"element","tag":"li","props":{},"children":[{"type":"text","value":"ipconfig/displaydns 查看DNS解析记录"}]},{"type":"element","tag":"li","props":{},"children":[{"type":"text","value":"ipconfig/flushdns 清除DNS解析记录"}]},{"type":"element","tag":"li","props":{},"children":[{"type":"text","value":"com口或者trunk口 Serial协议"}]},{"type":"element","tag":"li","props":{},"children":[{"type":"text","value":"回环控,业务口 ; FBI 军情六处MI6 国防部"}]}]},{"type":"element","tag":"h2","props":{"id":"会话管理console"},"children":[{"type":"text","value":"会话管理Console"}]},{"type":"element","tag":"ul","props":{},"children":[{"type":"element","tag":"li","props":{},"children":[{"type":"text","value":"链接线缆-> 设备管理器找到COM管理"}]}]}],"toc":{"title":"","searchDepth":2,"depth":2,"links":[{"id":"应用层概述","depth":2,"text":"应用层概述"},{"id":"常用的网络协议","depth":2,"text":"常用的网络协议"},{"id":"dns-domains-names-servers-域名解析系统","depth":2,"text":"DNS Domains Names Servers 域名解析系统"},{"id":"dns解析过程","depth":2,"text":"DNS解析过程"},{"id":"会话管理console","depth":2,"text":"会话管理Console"}]}},"_type":"markdown","_id":"content:7.networkengineer:1.dns.md","_source":"content","_file":"7.networkengineer/1.dns.md","_extension":"md"}