{"_path":"/outher","_dir":{"_path":"/outher/_dir","title":"其他","icon":"line-md:uploading-loop"},"_draft":false,"_partial":false,"_locale":"","title":"其他","description":"","body":{"type":"root","children":[{"type":"element","tag":"h1","props":{"id":"其他"},"children":[{"type":"text","value":"其他"}]},{"type":"element","tag":"ul","props":{},"children":[{"type":"element","tag":"li","props":{},"children":[{"type":"text","value":"095136 农业工程与信息技术"}]},{"type":"element","tag":"li","props":{},"children":[{"type":"text","value":"1.101思想政治 204英语二 341-2农业知识综合三 4.840数据库原理及应用"}]},{"type":"element","tag":"li","props":{},"children":[{"type":"text","value":"导师： 陈飞翔 陈钊 范光鹏 李昀 苏晓慧 王海燕 曾怡"}]}]}],"toc":{"title":"","searchDepth":2,"depth":2,"links":[]}},"_type":"markdown","_id":"content:7.outher:index.md","_source":"content","_file":"7.outher/index.md","_extension":"md"}